scorev.py
scorev-0.0.5.dist-info/METADATA
scorev-0.0.5.dist-info/WHEEL
scorev-0.0.5.dist-info/entry_points.txt
scorev-0.0.5.dist-info/top_level.txt
scorev-0.0.5.dist-info/RECORD
