Metadata-Version: 2.1
Name: scorev
Version: 0.0.5
Summary: A package for scoring policies of covid-19 with vaccine rates
Home-page: https://github.com/y-takefuji/scorev
Author: yoshiyasu takefuji
Author-email: takefuji@keio.jp
License: UNKNOWN
Project-URL: Bug Tracker, https://github.com/y-takefuji/scorev
Platform: UNKNOWN
Classifier: Programming Language :: Python :: 3
Classifier: License :: OSI Approved :: MIT License
Classifier: Operating System :: OS Independent
Requires-Python: >=3.8
